[
  {
    "id": 543975,
    "daily_installs": 0,
    "total_installs": 0,
    "fan_score": "5.0",
    "good_ratings": 0,
    "ok_ratings": 0,
    "bad_ratings": 0,
    "created_at": "2025-07-29T11:36:11.000Z",
    "code_updated_at": "2025-08-04T12:12:24.000Z",
    "namespace": "https://github.com/nbolton/github-triage-helper",
    "support_url": null,
    "contribution_url": null,
    "contribution_amount": null,
    "users": [
      {
        "id": 911974,
        "name": "nbolton",
        "created_at": "2022-05-08T20:18:55.000Z",
        "url": "https://greasyfork.org/users/911974-nbolton"
      }
    ],
    "name": "GitHub Issue Triage Helper",
    "description": "Suggest triage questions for GitHub issues using AI",
    "url": "https://greasyfork.org/scripts/543975-github-issue-triage-helper",
    "code_url": "https://update.greasyfork.org/scripts/543975/GitHub%20Issue%20Triage%20Helper.user.js",
    "code_size": 10722,
    "license": "MIT License",
    "version": "0.6",
    "locale": "en",
    "deleted": false,
    "visibility": "public"
  },
  {
    "id": 543958,
    "daily_installs": 0,
    "total_installs": 6,
    "fan_score": "5.0",
    "good_ratings": 0,
    "ok_ratings": 0,
    "bad_ratings": 0,
    "created_at": "2025-07-29T08:34:00.000Z",
    "code_updated_at": "2025-12-15T13:35:13.000Z",
    "namespace": "https://github.com/nbolton/github-review-shortcut",
    "support_url": null,
    "contribution_url": null,
    "contribution_amount": null,
    "users": [
      {
        "id": 911974,
        "name": "nbolton",
        "created_at": "2022-05-08T20:18:55.000Z",
        "url": "https://greasyfork.org/users/911974-nbolton"
      }
    ],
    "name": "GitHub PR review keyboard shortcut",
    "description": "Mark file as \"viewed\" on GitHub PR UI when hovering and pressing 'Escape' key",
    "url": "https://greasyfork.org/scripts/543958-github-pr-review-keyboard-shortcut",
    "code_url": "https://update.greasyfork.org/scripts/543958/GitHub%20PR%20review%20keyboard%20shortcut.user.js",
    "code_size": 2332,
    "license": "MIT License",
    "version": "0.3",
    "locale": "en",
    "deleted": false,
    "visibility": "public"
  },
  {
    "id": 444701,
    "daily_installs": 0,
    "total_installs": 9,
    "fan_score": "5.0",
    "good_ratings": 0,
    "ok_ratings": 0,
    "bad_ratings": 0,
    "created_at": "2022-05-08T20:20:54.000Z",
    "code_updated_at": "2022-06-28T12:48:11.000Z",
    "namespace": "https://github.com/symless/zendesk-fixer",
    "support_url": null,
    "contribution_url": null,
    "contribution_amount": null,
    "users": [
      {
        "id": 911974,
        "name": "nbolton",
        "created_at": "2022-05-08T20:18:55.000Z",
        "url": "https://greasyfork.org/users/911974-nbolton"
      }
    ],
    "name": "Symless Zendesk Fixer",
    "description": "Make Zendesk UX less painful/horrifying.",
    "url": "https://greasyfork.org/scripts/444701-symless-zendesk-fixer",
    "code_url": "https://update.greasyfork.org/scripts/444701/Symless%20Zendesk%20Fixer.user.js",
    "code_size": 18457,
    "license": "MIT License",
    "version": "0.2.8",
    "locale": "en",
    "deleted": false,
    "visibility": "unknown"
  }
]
