{
  "id": 404053,
  "daily_installs": 0,
  "total_installs": 3,
  "fan_score": "5.0",
  "good_ratings": 0,
  "ok_ratings": 0,
  "bad_ratings": 0,
  "created_at": "2020-05-25T01:09:38.000Z",
  "code_updated_at": "2020-05-25T01:09:38.000Z",
  "namespace": "http://seamonster.me",
  "support_url": null,
  "contribution_url": null,
  "contribution_amount": null,
  "users": [
    {
      "id": 547000,
      "name": "孤独的海怪",
      "created_at": "2020-04-30T05:16:50.000Z",
      "url": "https://greasyfork.org/users/547000-%E5%AD%A4%E7%8B%AC%E7%9A%84%E6%B5%B7%E6%80%AA",
      "scripts": [
        {
          "id": 402306,
          "daily_installs": 0,
          "total_installs": 31,
          "fan_score": "5.0",
          "good_ratings": 0,
          "ok_ratings": 0,
          "bad_ratings": 0,
          "created_at": "2020-04-30T05:19:56.000Z",
          "code_updated_at": "2020-06-23T03:37:11.000Z",
          "namespace": "http://wenyi.me",
          "support_url": null,
          "contribution_url": null,
          "contribution_amount": null,
          "name": "Geekhub scrollTop",
          "description": "Geekhub 返回顶部",
          "url": "https://greasyfork.org/scripts/402306-geekhub-scrolltop",
          "code_url": "https://update.greasyfork.org/scripts/402306/Geekhub%20scrollTop.user.js",
          "code_size": 1578,
          "license": null,
          "version": "0.4",
          "locale": "zh-CN",
          "deleted": false
        },
        {
          "id": 403705,
          "daily_installs": 0,
          "total_installs": 27,
          "fan_score": "5.0",
          "good_ratings": 0,
          "ok_ratings": 0,
          "bad_ratings": 0,
          "created_at": "2020-05-19T02:01:36.000Z",
          "code_updated_at": "2020-05-19T02:01:35.000Z",
          "namespace": "http://seamonster.me",
          "support_url": null,
          "contribution_url": null,
          "contribution_amount": null,
          "name": "GeekHub ColorInput",
          "description": "让你在Geekhub更动感的摸鱼",
          "url": "https://greasyfork.org/scripts/403705-geekhub-colorinput",
          "code_url": "https://update.greasyfork.org/scripts/403705/GeekHub%20ColorInput.user.js",
          "code_size": 1062,
          "license": null,
          "version": "0.1",
          "locale": "zh-CN",
          "deleted": false
        },
        {
          "id": 404053,
          "daily_installs": 0,
          "total_installs": 3,
          "fan_score": "5.0",
          "good_ratings": 0,
          "ok_ratings": 0,
          "bad_ratings": 0,
          "created_at": "2020-05-25T01:09:38.000Z",
          "code_updated_at": "2020-05-25T01:09:38.000Z",
          "namespace": "http://seamonster.me",
          "support_url": null,
          "contribution_url": null,
          "contribution_amount": null,
          "name": "GeekHub ContentBreak",
          "description": "修复GeekHub帖子内容变形",
          "url": "https://greasyfork.org/scripts/404053-geekhub-contentbreak",
          "code_url": "https://update.greasyfork.org/scripts/404053/GeekHub%20ContentBreak.user.js",
          "code_size": 514,
          "license": null,
          "version": "0.1",
          "locale": "zh-CN",
          "deleted": false
        },
        {
          "id": 408727,
          "daily_installs": 0,
          "total_installs": 10,
          "fan_score": "5.0",
          "good_ratings": 0,
          "ok_ratings": 0,
          "bad_ratings": 0,
          "created_at": "2020-08-14T09:14:04.000Z",
          "code_updated_at": "2020-08-14T09:14:04.000Z",
          "namespace": "http://seamonster.me",
          "support_url": null,
          "contribution_url": null,
          "contribution_amount": null,
          "name": "GeekHub upLoadImage",
          "description": "快捷上传图片",
          "url": "https://greasyfork.org/scripts/408727-geekhub-uploadimage",
          "code_url": "https://update.greasyfork.org/scripts/408727/GeekHub%20upLoadImage.user.js",
          "code_size": 5443,
          "license": null,
          "version": "0.1",
          "locale": "en",
          "deleted": false
        }
      ]
    }
  ],
  "name": "GeekHub ContentBreak",
  "description": "修复GeekHub帖子内容变形",
  "url": "https://greasyfork.org/scripts/404053-geekhub-contentbreak",
  "code_url": "https://update.greasyfork.org/scripts/404053/GeekHub%20ContentBreak.user.js",
  "code_size": 514,
  "license": null,
  "version": "0.1",
  "locale": "zh-CN",
  "deleted": false,
  "visibility": "public"
}
