{
  "id": 537281,
  "daily_installs": 0,
  "total_installs": 7,
  "fan_score": "5.0",
  "good_ratings": 0,
  "ok_ratings": 0,
  "bad_ratings": 0,
  "created_at": "2025-05-26T04:37:52.000Z",
  "code_updated_at": "2025-05-26T04:37:52.000Z",
  "namespace": "New Jack redoes agar.io after 10 years",
  "support_url": null,
  "contribution_url": null,
  "contribution_amount": null,
  "users": [
    {
      "id": 1474851,
      "name": "Jesid",
      "created_at": "2025-05-25T23:41:46.000Z",
      "url": "https://greasyfork.org/users/1474851-jesid",
      "scripts": [
        {
          "id": 537281,
          "daily_installs": 0,
          "total_installs": 7,
          "fan_score": "5.0",
          "good_ratings": 0,
          "ok_ratings": 0,
          "bad_ratings": 0,
          "created_at": "2025-05-26T04:37:52.000Z",
          "code_updated_at": "2025-05-26T04:37:52.000Z",
          "namespace": "New Jack redoes agar.io after 10 years",
          "support_url": null,
          "contribution_url": null,
          "contribution_amount": null,
          "name": "Piccolo's Agario Modded 3.2",
          "description": "Advanced controls, features, freeze/pause, change everyones skins, vertical split, use urls as skins",
          "url": "https://greasyfork.org/scripts/537281-piccolo-s-agario-modded-3-2",
          "code_url": "https://update.greasyfork.org/scripts/537281/Piccolo%27s%20Agario%20Modded%2032.user.js",
          "code_size": 150791,
          "license": "MIT License",
          "version": "3.1",
          "locale": "en",
          "deleted": false
        },
        {
          "id": 537345,
          "daily_installs": 0,
          "total_installs": 2,
          "fan_score": "5.0",
          "good_ratings": 0,
          "ok_ratings": 0,
          "bad_ratings": 0,
          "created_at": "2025-05-26T15:43:39.000Z",
          "code_updated_at": "2025-05-26T15:43:39.000Z",
          "namespace": "New Jack redoes agar.io after 10 years",
          "support_url": null,
          "contribution_url": null,
          "contribution_amount": null,
          "name": "Piccolo's Agario Modded 3.2",
          "description": "Advanced controls, features, freeze/pause, change everyones skins, vertical split, use urls as skins",
          "url": "https://greasyfork.org/scripts/537345-piccolo-s-agario-modded-3-2",
          "code_url": "https://update.greasyfork.org/scripts/537345/Piccolo%27s%20Agario%20Modded%2032.user.js",
          "code_size": 150026,
          "license": "MIT License",
          "version": "3.1",
          "locale": "en",
          "deleted": false
        },
        {
          "id": 537359,
          "daily_installs": 1,
          "total_installs": 31,
          "fan_score": "5.0",
          "good_ratings": 0,
          "ok_ratings": 0,
          "bad_ratings": 0,
          "created_at": "2025-05-26T17:43:47.000Z",
          "code_updated_at": "2025-05-26T17:43:46.000Z",
          "namespace": "New Jack redoes agar.io after 10 years",
          "support_url": null,
          "contribution_url": null,
          "contribution_amount": null,
          "name": "Piccolo's Agario Modded 3.2",
          "description": "Advanced controls, features, freeze/pause, change everyones skins, vertical split, use urls as skins",
          "url": "https://greasyfork.org/scripts/537359-piccolo-s-agario-modded-3-2",
          "code_url": "https://update.greasyfork.org/scripts/537359/Piccolo%27s%20Agario%20Modded%2032.user.js",
          "code_size": 151747,
          "license": "MIT License",
          "version": "3.1",
          "locale": "en",
          "deleted": false
        },
        {
          "id": 537584,
          "daily_installs": 0,
          "total_installs": 36,
          "fan_score": "5.0",
          "good_ratings": 0,
          "ok_ratings": 0,
          "bad_ratings": 0,
          "created_at": "2025-05-28T22:49:30.000Z",
          "code_updated_at": "2025-05-28T22:49:30.000Z",
          "namespace": "agario-custom-skin",
          "support_url": null,
          "contribution_url": null,
          "contribution_amount": null,
          "name": "Agar.io Custom Skin + Color Border",
          "description": "Subir imagen personalizada con borde blanco o negro (según color 1 o 2) y botón debajo de los colores.",
          "url": "https://greasyfork.org/scripts/537584-agar-io-custom-skin-color-border",
          "code_url": "https://update.greasyfork.org/scripts/537584/Agario%20Custom%20Skin%20%2B%20Color%20Border.user.js",
          "code_size": 3814,
          "license": null,
          "version": "1.0",
          "locale": "es",
          "deleted": false
        },
        {
          "id": 537681,
          "daily_installs": 0,
          "total_installs": 3,
          "fan_score": "5.0",
          "good_ratings": 0,
          "ok_ratings": 0,
          "bad_ratings": 0,
          "created_at": "2025-05-29T20:00:26.000Z",
          "code_updated_at": "2025-05-29T20:00:26.000Z",
          "namespace": "http://tampermonkey.net/",
          "support_url": null,
          "contribution_url": null,
          "contribution_amount": null,
          "name": "Agar.io image to custom skin + border colors",
          "description": "Upload image for custom skin with selectable border (white for color 1, black for color 2)",
          "url": "https://greasyfork.org/scripts/537681-agar-io-image-to-custom-skin-border-colors",
          "code_url": "https://update.greasyfork.org/scripts/537681/Agario%20image%20to%20custom%20skin%20%2B%20border%20colors.user.js",
          "code_size": 2948,
          "license": "MIT License",
          "version": "0.9",
          "locale": "en",
          "deleted": false
        },
        {
          "id": 537890,
          "daily_installs": 0,
          "total_installs": 3,
          "fan_score": "5.0",
          "good_ratings": 0,
          "ok_ratings": 0,
          "bad_ratings": 0,
          "created_at": "2025-05-31T19:31:13.000Z",
          "code_updated_at": "2025-05-31T19:31:12.000Z",
          "namespace": "http://tampermonkey.net/",
          "support_url": null,
          "contribution_url": null,
          "contribution_amount": null,
          "name": "Agar.io Custom Skin with Border (White/Black)",
          "description": "Subir una imagen y añadir borde blanco o negro en Agar.io",
          "url": "https://greasyfork.org/scripts/537890-agar-io-custom-skin-with-border-white-black",
          "code_url": "https://update.greasyfork.org/scripts/537890/Agario%20Custom%20Skin%20with%20Border%20%28WhiteBlack%29.user.js",
          "code_size": 5153,
          "license": null,
          "version": "0.1",
          "locale": "en",
          "deleted": false
        },
        {
          "id": 537907,
          "daily_installs": 0,
          "total_installs": 9,
          "fan_score": "5.0",
          "good_ratings": 0,
          "ok_ratings": 0,
          "bad_ratings": 0,
          "created_at": "2025-05-31T23:53:53.000Z",
          "code_updated_at": "2025-05-31T23:53:53.000Z",
          "namespace": "http://tampermonkey.net/",
          "support_url": null,
          "contribution_url": null,
          "contribution_amount": null,
          "name": "Agar.io Custom Skin Border",
          "description": "Agrega bordes personalizables a las skins en Agar.io, ubicando los botones junto al selector de color de la skin.",
          "url": "https://greasyfork.org/scripts/537907-agar-io-custom-skin-border",
          "code_url": "https://update.greasyfork.org/scripts/537907/Agario%20Custom%20Skin%20Border.user.js",
          "code_size": 4586,
          "license": null,
          "version": "0.2",
          "locale": "en",
          "deleted": false
        },
        {
          "id": 537908,
          "daily_installs": 0,
          "total_installs": 34,
          "fan_score": "5.0",
          "good_ratings": 0,
          "ok_ratings": 0,
          "bad_ratings": 0,
          "created_at": "2025-06-01T00:10:15.000Z",
          "code_updated_at": "2025-06-01T00:13:59.000Z",
          "namespace": "https://tampermonkey.net/",
          "support_url": null,
          "contribution_url": null,
          "contribution_amount": null,
          "name": "Agario Custom Skin (borde real junto a Save)",
          "description": "Subir imagen personalizada con borde del color elegido, botón junto a \"Save\"",
          "url": "https://greasyfork.org/scripts/537908-agario-custom-skin-borde-real-junto-a-save",
          "code_url": "https://update.greasyfork.org/scripts/537908/Agario%20Custom%20Skin%20%28borde%20real%20junto%20a%20Save%29.user.js",
          "code_size": 2673,
          "license": null,
          "version": "1.1",
          "locale": "en",
          "deleted": false
        },
        {
          "id": 538034,
          "daily_installs": 0,
          "total_installs": 7,
          "fan_score": "5.0",
          "good_ratings": 0,
          "ok_ratings": 0,
          "bad_ratings": 0,
          "created_at": "2025-06-02T02:03:44.000Z",
          "code_updated_at": "2025-06-02T02:03:44.000Z",
          "namespace": "http://tampermonkey.net/",
          "support_url": null,
          "contribution_url": null,
          "contribution_amount": null,
          "name": "Skin Border Mejorado",
          "description": "Aplica automáticamente un borde circular a la skin en Agar.io y permite descargarla.",
          "url": "https://greasyfork.org/scripts/538034-skin-border-mejorado",
          "code_url": "https://update.greasyfork.org/scripts/538034/Skin%20Border%20Mejorado.user.js",
          "code_size": 3966,
          "license": null,
          "version": "0.3",
          "locale": "es",
          "deleted": false
        }
      ]
    }
  ],
  "name": "Piccolo's Agario Modded 3.2",
  "description": "Advanced controls, features, freeze/pause, change everyones skins, vertical split, use urls as skins",
  "url": "https://greasyfork.org/scripts/537281-piccolo-s-agario-modded-3-2",
  "code_url": "https://update.greasyfork.org/scripts/537281/Piccolo%27s%20Agario%20Modded%2032.user.js",
  "code_size": 150791,
  "license": "MIT License",
  "version": "3.1",
  "locale": "en",
  "deleted": false,
  "visibility": "public"
}
